{
  "openapi": "3.0.4",
  "info": {
    "title": "SongCheng",
    "version": "1.0"
  },
  "paths": {
    "/api/Address/by-client/{clientId}": {
      "get": {
        "tags": [
          "Address"
        ],
        "parameters": [
          {
            "name": "clientId",
            "in": "path",
            "required": true,
            "schema": {
              "type": "integer",
              "format": "int32"
            }
          }
        ],
        "responses": {
          "200": {
            "description": "OK",
            "content": {
              "text/plain": {
                "schema": {
                  "$ref": "#/components/schemas/Address"
                }
              },
              "application/json": {
                "schema": {
                  "$ref": "#/components/schemas/Address"
                }
              },
              "text/json": {
                "schema": {
                  "$ref": "#/components/schemas/Address"
                }
              }
            }
          }
        }
      }
    },
    "/api/Address": {
      "post": {
        "tags": [
          "Address"
        ],
        "requestBody": {
          "content": {
            "application/json": {
              "schema": {
                "$ref": "#/components/schemas/Address"
              }
            },
            "text/json": {
              "schema": {
                "$ref": "#/components/schemas/Address"
              }
            },
            "application/*+json": {
              "schema": {
                "$ref": "#/components/schemas/Address"
              }
            }
          }
        },
        "responses": {
          "200": {
            "description": "OK",
            "content": {
              "text/plain": {
                "schema": {
                  "$ref": "#/components/schemas/Address"
                }
              },
              "application/json": {
                "schema": {
                  "$ref": "#/components/schemas/Address"
                }
              },
              "text/json": {
                "schema": {
                  "$ref": "#/components/schemas/Address"
                }
              }
            }
          }
        }
      }
    },
    "/api/Address/{id}": {
      "delete": {
        "tags": [
          "Address"
        ],
        "parameters": [
          {
            "name": "id",
            "in": "path",
            "required": true,
            "schema": {
              "type": "integer",
              "format": "int32"
            }
          }
        ],
        "responses": {
          "200": {
            "description": "OK"
          }
        }
      }
    },
    "/api/Auth/login": {
      "post": {
        "tags": [
          "Auth"
        ],
        "requestBody": {
          "content": {
            "application/json": {
              "schema": {
                "$ref": "#/components/schemas/LoginDto"
              }
            },
            "text/json": {
              "schema": {
                "$ref": "#/components/schemas/LoginDto"
              }
            },
            "application/*+json": {
              "schema": {
                "$ref": "#/components/schemas/LoginDto"
              }
            }
          }
        },
        "responses": {
          "200": {
            "description": "OK"
          }
        }
      }
    },
    "/api/Categories": {
      "get": {
        "tags": [
          "Categories"
        ],
        "responses": {
          "200": {
            "description": "OK",
            "content": {
              "text/plain": {
                "schema": {
                  "type": "array",
                  "items": {
                    "$ref": "#/components/schemas/Category"
                  }
                }
              },
              "application/json": {
                "schema": {
                  "type": "array",
                  "items": {
                    "$ref": "#/components/schemas/Category"
                  }
                }
              },
              "text/json": {
                "schema": {
                  "type": "array",
                  "items": {
                    "$ref": "#/components/schemas/Category"
                  }
                }
              }
            }
          }
        }
      },
      "post": {
        "tags": [
          "Categories"
        ],
        "requestBody": {
          "content": {
            "application/json": {
              "schema": {
                "$ref": "#/components/schemas/Category"
              }
            },
            "text/json": {
              "schema": {
                "$ref": "#/components/schemas/Category"
              }
            },
            "application/*+json": {
              "schema": {
                "$ref": "#/components/schemas/Category"
              }
            }
          }
        },
        "responses": {
          "200": {
            "description": "OK",
            "content": {
              "text/plain": {
                "schema": {
                  "$ref": "#/components/schemas/Category"
                }
              },
              "application/json": {
                "schema": {
                  "$ref": "#/components/schemas/Category"
                }
              },
              "text/json": {
                "schema": {
                  "$ref": "#/components/schemas/Category"
                }
              }
            }
          }
        }
      }
    },
    "/api/Categories/{id}": {
      "get": {
        "tags": [
          "Categories"
        ],
        "parameters": [
          {
            "name": "id",
            "in": "path",
            "required": true,
            "schema": {
              "type": "integer",
              "format": "int32"
            }
          }
        ],
        "responses": {
          "200": {
            "description": "OK",
            "content": {
              "text/plain": {
                "schema": {
                  "$ref": "#/components/schemas/Category"
                }
              },
              "application/json": {
                "schema": {
                  "$ref": "#/components/schemas/Category"
                }
              },
              "text/json": {
                "schema": {
                  "$ref": "#/components/schemas/Category"
                }
              }
            }
          }
        }
      },
      "delete": {
        "tags": [
          "Categories"
        ],
        "parameters": [
          {
            "name": "id",
            "in": "path",
            "required": true,
            "schema": {
              "type": "integer",
              "format": "int32"
            }
          }
        ],
        "responses": {
          "200": {
            "description": "OK"
          }
        }
      }
    },
    "/api/Clients": {
      "get": {
        "tags": [
          "Clients"
        ],
        "responses": {
          "200": {
            "description": "OK",
            "content": {
              "text/plain": {
                "schema": {
                  "type": "array",
                  "items": {
                    "$ref": "#/components/schemas/Client"
                  }
                }
              },
              "application/json": {
                "schema": {
                  "type": "array",
                  "items": {
                    "$ref": "#/components/schemas/Client"
                  }
                }
              },
              "text/json": {
                "schema": {
                  "type": "array",
                  "items": {
                    "$ref": "#/components/schemas/Client"
                  }
                }
              }
            }
          }
        }
      }
    },
    "/api/Clients/{id}": {
      "get": {
        "tags": [
          "Clients"
        ],
        "parameters": [
          {
            "name": "id",
            "in": "path",
            "required": true,
            "schema": {
              "type": "integer",
              "format": "int32"
            }
          }
        ],
        "responses": {
          "200": {
            "description": "OK",
            "content": {
              "text/plain": {
                "schema": {
                  "$ref": "#/components/schemas/Client"
                }
              },
              "application/json": {
                "schema": {
                  "$ref": "#/components/schemas/Client"
                }
              },
              "text/json": {
                "schema": {
                  "$ref": "#/components/schemas/Client"
                }
              }
            }
          }
        }
      },
      "delete": {
        "tags": [
          "Clients"
        ],
        "parameters": [
          {
            "name": "id",
            "in": "path",
            "required": true,
            "schema": {
              "type": "integer",
              "format": "int32"
            }
          }
        ],
        "responses": {
          "200": {
            "description": "OK"
          }
        }
      }
    },
    "/api/Clients/register": {
      "post": {
        "tags": [
          "Clients"
        ],
        "requestBody": {
          "content": {
            "application/json": {
              "schema": {
                "$ref": "#/components/schemas/Client"
              }
            },
            "text/json": {
              "schema": {
                "$ref": "#/components/schemas/Client"
              }
            },
            "application/*+json": {
              "schema": {
                "$ref": "#/components/schemas/Client"
              }
            }
          }
        },
        "responses": {
          "200": {
            "description": "OK"
          }
        }
      }
    },
    "/api/Ingredients": {
      "get": {
        "tags": [
          "Ingredients"
        ],
        "responses": {
          "200": {
            "description": "OK",
            "content": {
              "text/plain": {
                "schema": {
                  "type": "array",
                  "items": {
                    "$ref": "#/components/schemas/Ingredient"
                  }
                }
              },
              "application/json": {
                "schema": {
                  "type": "array",
                  "items": {
                    "$ref": "#/components/schemas/Ingredient"
                  }
                }
              },
              "text/json": {
                "schema": {
                  "type": "array",
                  "items": {
                    "$ref": "#/components/schemas/Ingredient"
                  }
                }
              }
            }
          }
        }
      },
      "post": {
        "tags": [
          "Ingredients"
        ],
        "requestBody": {
          "content": {
            "application/json": {
              "schema": {
                "$ref": "#/components/schemas/Ingredient"
              }
            },
            "text/json": {
              "schema": {
                "$ref": "#/components/schemas/Ingredient"
              }
            },
            "application/*+json": {
              "schema": {
                "$ref": "#/components/schemas/Ingredient"
              }
            }
          }
        },
        "responses": {
          "200": {
            "description": "OK",
            "content": {
              "text/plain": {
                "schema": {
                  "$ref": "#/components/schemas/Ingredient"
                }
              },
              "application/json": {
                "schema": {
                  "$ref": "#/components/schemas/Ingredient"
                }
              },
              "text/json": {
                "schema": {
                  "$ref": "#/components/schemas/Ingredient"
                }
              }
            }
          }
        }
      }
    },
    "/api/Ingredients/{id}": {
      "delete": {
        "tags": [
          "Ingredients"
        ],
        "parameters": [
          {
            "name": "id",
            "in": "path",
            "required": true,
            "schema": {
              "type": "integer",
              "format": "int32"
            }
          }
        ],
        "responses": {
          "200": {
            "description": "OK"
          }
        }
      }
    },
    "/api/Orders": {
      "get": {
        "tags": [
          "Orders"
        ],
        "responses": {
          "200": {
            "description": "OK",
            "content": {
              "text/plain": {
                "schema": {
                  "type": "array",
                  "items": {
                    "$ref": "#/components/schemas/OrderDto"
                  }
                }
              },
              "application/json": {
                "schema": {
                  "type": "array",
                  "items": {
                    "$ref": "#/components/schemas/OrderDto"
                  }
                }
              },
              "text/json": {
                "schema": {
                  "type": "array",
                  "items": {
                    "$ref": "#/components/schemas/OrderDto"
                  }
                }
              }
            }
          }
        }
      },
      "post": {
        "tags": [
          "Orders"
        ],
        "requestBody": {
          "content": {
            "application/json": {
              "schema": {
                "$ref": "#/components/schemas/CreateOrderDto"
              }
            },
            "text/json": {
              "schema": {
                "$ref": "#/components/schemas/CreateOrderDto"
              }
            },
            "application/*+json": {
              "schema": {
                "$ref": "#/components/schemas/CreateOrderDto"
              }
            }
          }
        },
        "responses": {
          "200": {
            "description": "OK"
          }
        }
      }
    },
    "/api/Orders/{id}": {
      "get": {
        "tags": [
          "Orders"
        ],
        "parameters": [
          {
            "name": "id",
            "in": "path",
            "required": true,
            "schema": {
              "type": "integer",
              "format": "int32"
            }
          }
        ],
        "responses": {
          "200": {
            "description": "OK",
            "content": {
              "text/plain": {
                "schema": {
                  "$ref": "#/components/schemas/Order"
                }
              },
              "application/json": {
                "schema": {
                  "$ref": "#/components/schemas/Order"
                }
              },
              "text/json": {
                "schema": {
                  "$ref": "#/components/schemas/Order"
                }
              }
            }
          }
        }
      }
    },
    "/api/Products": {
      "get": {
        "tags": [
          "Products"
        ],
        "responses": {
          "200": {
            "description": "OK",
            "content": {
              "text/plain": {
                "schema": {
                  "type": "array",
                  "items": {
                    "$ref": "#/components/schemas/ProductDto"
                  }
                }
              },
              "application/json": {
                "schema": {
                  "type": "array",
                  "items": {
                    "$ref": "#/components/schemas/ProductDto"
                  }
                }
              },
              "text/json": {
                "schema": {
                  "type": "array",
                  "items": {
                    "$ref": "#/components/schemas/ProductDto"
                  }
                }
              }
            }
          }
        }
      }
    },
    "/api/Products/{id}": {
      "get": {
        "tags": [
          "Products"
        ],
        "parameters": [
          {
            "name": "id",
            "in": "path",
            "required": true,
            "schema": {
              "type": "integer",
              "format": "int32"
            }
          }
        ],
        "responses": {
          "200": {
            "description": "OK",
            "content": {
              "text/plain": {
                "schema": {
                  "$ref": "#/components/schemas/Product"
                }
              },
              "application/json": {
                "schema": {
                  "$ref": "#/components/schemas/Product"
                }
              },
              "text/json": {
                "schema": {
                  "$ref": "#/components/schemas/Product"
                }
              }
            }
          }
        }
      }
    }
  },
  "components": {
    "schemas": {
      "Address": {
        "type": "object",
        "properties": {
          "id": {
            "type": "integer",
            "format": "int32"
          },
          "name": {
            "type": "string",
            "nullable": true
          },
          "postalCode": {
            "type": "integer",
            "format": "int32"
          },
          "city": {
            "type": "string",
            "nullable": true
          },
          "clientId": {
            "type": "integer",
            "format": "int32"
          },
          "client": {
            "$ref": "#/components/schemas/Client"
          }
        },
        "additionalProperties": false
      },
      "Category": {
        "type": "object",
        "properties": {
          "id": {
            "type": "integer",
            "format": "int32"
          },
          "name": {
            "type": "string",
            "nullable": true
          },
          "description": {
            "type": "string",
            "nullable": true
          }
        },
        "additionalProperties": false
      },
      "Client": {
        "type": "object",
        "properties": {
          "id": {
            "type": "integer",
            "format": "int32"
          },
          "dni": {
            "type": "string",
            "nullable": true
          },
          "password": {
            "type": "string",
            "nullable": true
          },
          "name": {
            "type": "string",
            "nullable": true
          },
          "phone": {
            "type": "string",
            "nullable": true
          },
          "addresses": {
            "type": "array",
            "items": {
              "$ref": "#/components/schemas/Address"
            },
            "nullable": true
          }
        },
        "additionalProperties": false
      },
      "CreateOrderDto": {
        "type": "object",
        "properties": {
          "clientId": {
            "type": "integer",
            "format": "int32"
          },
          "items": {
            "type": "array",
            "items": {
              "$ref": "#/components/schemas/OrderItemDto"
            },
            "nullable": true
          }
        },
        "additionalProperties": false
      },
      "Ingredient": {
        "type": "object",
        "properties": {
          "id": {
            "type": "integer",
            "format": "int32"
          },
          "name": {
            "type": "string",
            "nullable": true
          },
          "description": {
            "type": "string",
            "nullable": true
          },
          "price": {
            "type": "number",
            "format": "double"
          },
          "productIngredients": {
            "type": "array",
            "items": {
              "$ref": "#/components/schemas/ProductIngredient"
            },
            "nullable": true
          }
        },
        "additionalProperties": false
      },
      "LoginDto": {
        "type": "object",
        "properties": {
          "user": {
            "type": "string",
            "nullable": true
          },
          "password": {
            "type": "string",
            "nullable": true
          }
        },
        "additionalProperties": false
      },
      "Order": {
        "type": "object",
        "properties": {
          "id": {
            "type": "integer",
            "format": "int32"
          },
          "date": {
            "type": "string",
            "format": "date-time"
          },
          "price": {
            "type": "number",
            "format": "double"
          },
          "type": {
            "type": "string",
            "nullable": true
          },
          "clientId": {
            "type": "integer",
            "format": "int32"
          },
          "client": {
            "$ref": "#/components/schemas/Client"
          },
          "orderDetails": {
            "type": "array",
            "items": {
              "$ref": "#/components/schemas/OrderDetail"
            },
            "nullable": true
          }
        },
        "additionalProperties": false
      },
      "OrderDetail": {
        "type": "object",
        "properties": {
          "orderId": {
            "type": "integer",
            "format": "int32"
          },
          "order": {
            "$ref": "#/components/schemas/Order"
          },
          "productId": {
            "type": "integer",
            "format": "int32"
          },
          "product": {
            "$ref": "#/components/schemas/Product"
          },
          "quantity": {
            "type": "integer",
            "format": "int32"
          },
          "price": {
            "type": "number",
            "format": "double"
          }
        },
        "additionalProperties": false
      },
      "OrderDetailDto": {
        "type": "object",
        "properties": {
          "productId": {
            "type": "integer",
            "format": "int32"
          },
          "productName": {
            "type": "string",
            "nullable": true
          },
          "quantity": {
            "type": "integer",
            "format": "int32"
          },
          "price": {
            "type": "number",
            "format": "double"
          }
        },
        "additionalProperties": false
      },
      "OrderDto": {
        "type": "object",
        "properties": {
          "id": {
            "type": "integer",
            "format": "int32"
          },
          "date": {
            "type": "string",
            "format": "date-time"
          },
          "price": {
            "type": "number",
            "format": "double"
          },
          "type": {
            "type": "string",
            "nullable": true
          },
          "clientId": {
            "type": "integer",
            "format": "int32"
          },
          "details": {
            "type": "array",
            "items": {
              "$ref": "#/components/schemas/OrderDetailDto"
            },
            "nullable": true
          }
        },
        "additionalProperties": false
      },
      "OrderItemDto": {
        "type": "object",
        "properties": {
          "productId": {
            "type": "integer",
            "format": "int32"
          },
          "quantity": {
            "type": "integer",
            "format": "int32"
          },
          "price": {
            "type": "number",
            "format": "double"
          }
        },
        "additionalProperties": false
      },
      "Product": {
        "type": "object",
        "properties": {
          "id": {
            "type": "integer",
            "format": "int32"
          },
          "name": {
            "type": "string",
            "nullable": true
          },
          "code": {
            "type": "string",
            "nullable": true
          },
          "description": {
            "type": "string",
            "nullable": true
          },
          "price": {
            "type": "number",
            "format": "double"
          },
          "categoryId": {
            "type": "integer",
            "format": "int32"
          },
          "productIngredients": {
            "type": "array",
            "items": {
              "$ref": "#/components/schemas/ProductIngredient"
            },
            "nullable": true
          }
        },
        "additionalProperties": false
      },
      "ProductDto": {
        "type": "object",
        "properties": {
          "id": {
            "type": "integer",
            "format": "int32"
          },
          "name": {
            "type": "string",
            "nullable": true
          },
          "code": {
            "type": "string",
            "nullable": true
          },
          "description": {
            "type": "string",
            "nullable": true
          },
          "price": {
            "type": "number",
            "format": "double"
          },
          "categoryId": {
            "type": "integer",
            "format": "int32"
          },
          "ingredients": {
            "type": "array",
            "items": {
              "type": "string"
            },
            "nullable": true
          }
        },
        "additionalProperties": false
      },
      "ProductIngredient": {
        "type": "object",
        "properties": {
          "productId": {
            "type": "integer",
            "format": "int32"
          },
          "product": {
            "$ref": "#/components/schemas/Product"
          },
          "ingredientId": {
            "type": "integer",
            "format": "int32"
          },
          "ingredient": {
            "$ref": "#/components/schemas/Ingredient"
          },
          "quantity": {
            "type": "number",
            "format": "double",
            "nullable": true
          }
        },
        "additionalProperties": false
      }
    }
  }
}